pipeline_csv/__init__.py
pipeline_csv/oegiv.py
pipeline_csv/orientation.py
pipeline_csv/csvfile/README.md
pipeline_csv/csvfile/__init__.py
pipeline_csv/csvfile/defect.py
pipeline_csv/csvfile/row.py
pipeline_csv/csvfile/tubes.py
pipeline_csv/csvfile/statistics/__init__.py
pipeline_csv/csvfile/statistics/defects.py
pipeline_csv/csvfile/statistics/pipes.py
pipeline_csv/csvfile/statistics/totals.py
pipeline_csv-1.20.dist-info/licenses/LICENSE
pipeline_csv-1.20.dist-info/METADATA
pipeline_csv-1.20.dist-info/WHEEL
pipeline_csv-1.20.dist-info/top_level.txt
pipeline_csv-1.20.dist-info/RECORD
