Metadata-Version: 2.4
Name: pipeline_csv
Version: 1.20
Summary: Pipeline inline inspection data as CSV file.
Home-page: https://github.com/vb64/pipeline.csv
Author: Vitaly Bogomolov
Author-email: mail@vitaly-bogomolov.ru
Project-URL: Bug Tracker, https://github.com/vb64/pipeline.csv/issues
Classifier: Programming Language :: Python :: 3
Classifier: License :: OSI Approved :: MIT License
Classifier: Operating System :: OS Independent
Requires-Python: >=3.6
License-File: LICENSE
Dynamic: license-file
